amplify_bbopt/__init__.py
amplify_bbopt/__version__.py
amplify_bbopt/amplify_model.py
amplify_bbopt/bbopt_logging.py
amplify_bbopt/blackbox.py
amplify_bbopt/encoder.py
amplify_bbopt/optimizer.py
amplify_bbopt/surrogate.py
amplify_bbopt/trainer.py
amplify_bbopt/variable.py
amplify_bbopt-1.0.3.dist-info/licenses/LICENSE
amplify_bbopt-1.0.3.dist-info/WHEEL
amplify_bbopt-1.0.3.dist-info/METADATA
amplify_bbopt-1.0.3.dist-info/RECORD
