Metadata-Version: 2.4
Name: amplify-bbopt
Version: 1.0.3
Summary: Black box optimization library based on Amplify SDK
Author: Fixstars Amplify Corporation
Author-email: Fixstars Amplify Corporation <y_matsuda@fixstars.com>
License-File: LICENSE
Classifier: Environment :: Console
Classifier: Development Status :: 4 - Beta
Classifier: Intended Audience :: Developers
Classifier: Intended Audience :: Science/Research
Classifier: Topic :: Software Development :: Libraries
Classifier: Topic :: Software Development :: Libraries :: Python Modules
Classifier: Topic :: Scientific/Engineering
Classifier: Topic :: Scientific/Engineering :: Artificial Intelligence
Classifier: Operating System :: POSIX :: Linux
Classifier: Operating System :: Microsoft :: Windows
Classifier: Operating System :: MacOS :: MacOS X
Classifier: License :: OSI Approved :: MIT License
Classifier: Programming Language :: Python
Classifier: Programming Language :: Python :: 3.10
Classifier: Programming Language :: Python :: 3.11
Classifier: Programming Language :: Python :: 3.12
Requires-Dist: amplify[extra]>=1.4.0
Requires-Dist: typing-extensions ; python_full_version < '3.11'
Requires-Dist: torch>=2.5.1
Maintainer: Yuki Minamoto, Takuma Saito, Yoshiki Matsuda
Maintainer-email: Yuki Minamoto <yuki.minamoto@fixstars.com>, Takuma Saito <takuma.saito@fixstars.com>, Yoshiki Matsuda <y_matsuda@fixstars.com>
Requires-Python: >=3.10
Project-URL: Changelog, https://amplify.fixstars.com/docs/amplify-bbopt/v1/changelog.html
Project-URL: Documentation, https://amplify.fixstars.com/docs/amplify-bbopt/v1/
Project-URL: Homepage, https://amplify.fixstars.com/
Project-URL: Tutorial, https://amplify.fixstars.com/demo
